aka_json/__init__.py
aka_json/constants.py
aka_json/decoder.py
aka_json/encoder.py
aka_json/exceptions.py
aka_json/file.py
aka_json-1.0.1.dist-info/METADATA
aka_json-1.0.1.dist-info/WHEEL
aka_json-1.0.1.dist-info/top_level.txt
aka_json-1.0.1.dist-info/RECORD
